ai_configurator/__init__.py
ai_configurator/cli.py
ai_configurator/cli_enhanced.py
ai_configurator/main.py
ai_configurator/version.py
ai_configurator/cli/__init__.py
ai_configurator/cli/agent_commands.py
ai_configurator/cli/cache_commands.py
ai_configurator/cli/enhanced_sync_commands.py
ai_configurator/cli/file_commands.py
ai_configurator/cli/git_commands.py
ai_configurator/cli/library_commands.py
ai_configurator/cli/mcp_commands.py
ai_configurator/cli/monitoring_commands.py
ai_configurator/cli/production_commands.py
ai_configurator/cli/registry_commands.py
ai_configurator/cli/sync_commands.py
ai_configurator/cli/system_commands.py
ai_configurator/cli/wizard_commands.py
ai_configurator/core/__init__.py
ai_configurator/core/agent_manager.py
ai_configurator/core/config.py
ai_configurator/core/file_utils.py
ai_configurator/core/library_manager.py
ai_configurator/core/logging_config.py
ai_configurator/core/production_config.py
ai_configurator/models/__init__.py
ai_configurator/models/agent.py
ai_configurator/models/configuration.py
ai_configurator/models/file_models.py
ai_configurator/models/library.py
ai_configurator/models/mcp_server.py
ai_configurator/models/registry_models.py
ai_configurator/models/sync_models.py
ai_configurator/models/value_objects.py
ai_configurator/models/wizard_models.py
ai_configurator/services/__init__.py
ai_configurator/services/agent_service.py
ai_configurator/services/cached_library_service.py
ai_configurator/services/config_service.py
ai_configurator/services/enhanced_sync_service.py
ai_configurator/services/file_service.py
ai_configurator/services/git_library_service.py
ai_configurator/services/library_service.py
ai_configurator/services/qcli_sync_service.py
ai_configurator/services/registry_service.py
ai_configurator/services/sync_service.py
ai_configurator/services/wizard_service.py
ai_configurator/tui/__init__.py
ai_configurator/tui/app.py
ai_configurator/tui/config.py
ai_configurator/tui/screens/__init__.py
ai_agent_manager-0.3.1.dist-info/METADATA
ai_agent_manager-0.3.1.dist-info/WHEEL
ai_agent_manager-0.3.1.dist-info/entry_points.txt
ai_agent_manager-0.3.1.dist-info/licenses/LICENSE
ai_agent_manager-0.3.1.dist-info/RECORD
