Metadata-Version: 2.4
Name: ai-agent-manager
Version: 0.3.1
Summary: Terminal UI for managing AI agents, resources, and MCP servers across multiple AI tools
Project-URL: Homepage, https://github.com/jschwellach/ai-configurator
Project-URL: Documentation, https://github.com/jschwellach/ai-configurator#readme
Project-URL: Repository, https://github.com/jschwellach/ai-configurator.git
Project-URL: Bug Tracker, https://github.com/jschwellach/ai-configurator/issues
Author: AI Configurator Team
License-Expression: MIT
License-File: LICENSE
Keywords: agents,ai,amazon-q,claude,configuration,knowledge-management,mcp,tui
Classifier: Development Status :: 4 - Beta
Classifier: Intended Audience :: Developers
Classifier: License :: OSI Approved :: MIT License
Classifier: Operating System :: OS Independent
Classifier: Programming Language :: Python :: 3
Classifier: Programming Language :: Python :: 3.9
Classifier: Programming Language :: Python :: 3.10
Classifier: Programming Language :: Python :: 3.11
Classifier: Programming Language :: Python :: 3.12
Classifier: Topic :: Software Development
Classifier: Topic :: System :: Installation/Setup
Requires-Python: >=3.9
Requires-Dist: click-default-group>=1.2.2
Requires-Dist: click>=8.0.0
Requires-Dist: gitpython>=3.1.0
Requires-Dist: jinja2>=3.0.0
Requires-Dist: jsonschema>=4.17.0
Requires-Dist: packaging>=21.0.0
Requires-Dist: platformdirs>=3.0.0
Requires-Dist: prompt-toolkit>=3.0.0
Requires-Dist: pydantic>=2.0.0
Requires-Dist: pyyaml>=6.0.0
Requires-Dist: requests>=2.28.0
Requires-Dist: rich>=13.0.0
Requires-Dist: textual>=0.40.0
Requires-Dist: tomli>=2.0.0; python_version < '3.11'
Requires-Dist: watchdog>=3.0.0
Provides-Extra: dev
Requires-Dist: black>=23.0.0; extra == 'dev'
Requires-Dist: flake8>=6.0.0; extra == 'dev'
Requires-Dist: isort>=5.0.0; extra == 'dev'
Requires-Dist: mypy>=1.0.0; extra == 'dev'
Requires-Dist: pre-commit>=3.0.0; extra == 'dev'
Requires-Dist: pytest-asyncio>=0.21.0; extra == 'dev'
Requires-Dist: pytest-cov>=4.0.0; extra == 'dev'
Requires-Dist: pytest-mock>=3.10.0; extra == 'dev'
Requires-Dist: pytest>=7.0.0; extra == 'dev'
Requires-Dist: textual-dev>=1.0.0; extra == 'dev'
